source_notion/__init__.py
source_notion/components.py
source_notion/manifest.yaml
source_notion/run.py
source_notion/schemas/blocks.json
source_notion/schemas/pages.json
source_notion/source.py
source_notion/spec.json
airbyte_source_notion-3.2.0.dist-info/METADATA
airbyte_source_notion-3.2.0.dist-info/WHEEL
airbyte_source_notion-3.2.0.dist-info/entry_points.txt
airbyte_source_notion-3.2.0.dist-info/RECORD
