Metadata-Version: 2.1
Name: airbyte-source-notion
Version: 3.2.0
Summary: Source implementation for Notion.
Home-page: https://airbyte.com
License: ELv2
Author: Airbyte
Author-email: contact@airbyte.io
Requires-Python: >=3.10,<3.12
Classifier: License :: Other/Proprietary License
Classifier: Programming Language :: Python :: 3
Classifier: Programming Language :: Python :: 3.10
Classifier: Programming Language :: Python :: 3.11
Requires-Dist: airbyte-cdk (>=7,<8)
Project-URL: Documentation, https://docs.airbyte.com/integrations/sources/notion
Project-URL: Repository, https://github.com/airbytehq/airbyte
